muddler/VERSION
muddler/__init__.py
muddler/config.py
muddler/muddle.py
muddler/unmuddle.py
muddler/utils.py
muddler/v1/__init__.py
muddler/v1/source_chain.py
muddler-0.1.3.dist-info/LICENSE
muddler-0.1.3.dist-info/METADATA
muddler-0.1.3.dist-info/WHEEL
muddler-0.1.3.dist-info/entry_points.txt
muddler-0.1.3.dist-info/top_level.txt
muddler-0.1.3.dist-info/RECORD
