Metadata-Version: 2.1
Name: muddler
Version: 0.1.3
Summary: The Muddler derived-file sharing utility.
Home-page: https://github.com/CAMeL-Lab/muddler.git
Author: Ossama W. Obeid
Author-email: oobeid@nyu.edu
Maintainer: Ossama W. Obeid
Maintainer-email: oobeid@nyu.edu
License: MIT
Classifier: Development Status :: 4 - Beta
Classifier: Environment :: Console
Classifier: Intended Audience :: Developers
Classifier: Intended Audience :: Education
Classifier: Intended Audience :: Information Technology
Classifier: Intended Audience :: Science/Research
Classifier: License :: OSI Approved :: MIT License
Classifier: Operating System :: OS Independent
Classifier: Programming Language :: Python :: 3
Classifier: Programming Language :: Python :: 3.7
Classifier: Programming Language :: Python :: 3.8
Classifier: Programming Language :: Python :: 3.9
Classifier: Programming Language :: Python :: 3.10
Classifier: Programming Language :: Python :: 3.11
License-File: LICENSE
